{
  "source": "when_in_rome",
  "file_path": "Corpus/Chamber_Other/Corelli,_Arcangelo/Op3No11/2/analysis.txt",
  "piece_id": "corelli_op3no11_2",
  "global_key": "g",
  "global_key_class": 19,
  "annotations": [
    {
      "measure": 1,
      "beat": 1.0,
      "key": "g",
      "key_class": 19,
      "numeral": "i"
    },
    {
      "measure": 1,
      "beat": 3.0,
      "key": "g",
      "key_class": 19,
      "numeral": "V"
    },
    {
      "measure": 2,
      "beat": 1.0,
      "key": "g",
      "key_class": 19,
      "numeral": "i"
    },
    {
      "measure": 2,
      "beat": 3.0,
      "key": "g",
      "key_class": 19,
      "numeral": "iv"
    },
    {
      "measure": 3,
      "beat": 1.0,
      "key": "g",
      "key_class": 19,
      "numeral": "VII"
    },
    {
      "measure": 3,
      "beat": 3.0,
      "key": "g",
      "key_class": 19,
      "numeral": "III"
    },
    {
      "measure": 4,
      "beat": 1.0,
      "key": "g",
      "key_class": 19,
      "numeral": "V[no3][add4]/III"
    },
    {
      "measure": 4,
      "beat": 2.0,
      "key": "g",
      "key_class": 19,
      "numeral": "V6/III"
    },
    {
      "measure": 4,
      "beat": 2.5,
      "key": "g",
      "key_class": 19,
      "numeral": "V65"
    },
    {
      "measure": 4,
      "beat": 3.0,
      "key": "g",
      "key_class": 19,
      "numeral": "i[add9]"
    },
    {
      "measure": 4,
      "beat": 4.0,
      "key": "g",
      "key_class": 19,
      "numeral": "i6"
    },
    {
      "measure": 5,
      "beat": 1.0,
      "key": "g",
      "key_class": 19,
      "numeral": "V[no3][add4]"
    },
    {
      "measure": 5,
      "beat": 2.0,
      "key": "g",
      "key_class": 19,
      "numeral": "V"
    },
    {
      "measure": 5,
      "beat": 3.0,
      "key": "g",
      "key_class": 19,
      "numeral": "iv6[no1][add2]"
    },
    {
      "measure": 5,
      "beat": 4.0,
      "key": "g",
      "key_class": 19,
      "numeral": "iv6"
    },
    {
      "measure": 5,
      "beat": 4.5,
      "key": "g",
      "key_class": 19,
      "numeral": "iio6"
    },
    {
      "measure": 6,
      "beat": 1.0,
      "key": "g",
      "key_class": 19,
      "numeral": "V7"
    },
    {
      "measure": 6,
      "beat": 2.0,
      "key": "g",
      "key_class": 19,
      "numeral": "VI"
    },
    {
      "measure": 6,
      "beat": 3.0,
      "key": "g",
      "key_class": 19,
      "numeral": "iiø65"
    },
    {
      "measure": 6,
      "beat": 4.0,
      "key": "g",
      "key_class": 19,
      "numeral": "V"
    },
    {
      "measure": 7,
      "beat": 1.0,
      "key": "g",
      "key_class": 19,
      "numeral": "i"
    },
    {
      "measure": 7,
      "beat": 2.0,
      "key": "g",
      "key_class": 19,
      "numeral": "V6"
    },
    {
      "measure": 7,
      "beat": 3.0,
      "key": "g",
      "key_class": 19,
      "numeral": "i"
    },
    {
      "measure": 7,
      "beat": 4.0,
      "key": "g",
      "key_class": 19,
      "numeral": "V6"
    },
    {
      "measure": 8,
      "beat": 1.0,
      "key": "g",
      "key_class": 19,
      "numeral": "i"
    },
    {
      "measure": 8,
      "beat": 1.5,
      "key": "g",
      "key_class": 19,
      "numeral": "I/III"
    },
    {
      "measure": 8,
      "beat": 2.0,
      "key": "g",
      "key_class": 19,
      "numeral": "V6/III"
    },
    {
      "measure": 8,
      "beat": 3.0,
      "key": "g",
      "key_class": 19,
      "numeral": "I/III"
    },
    {
      "measure": 8,
      "beat": 4.0,
      "key": "g",
      "key_class": 19,
      "numeral": "V6/III"
    },
    {
      "measure": 9,
      "beat": 1.0,
      "key": "g",
      "key_class": 19,
      "numeral": "I/III"
    },
    {
      "measure": 9,
      "beat": 1.5,
      "key": "g",
      "key_class": 19,
      "numeral": "i/iv"
    },
    {
      "measure": 9,
      "beat": 2.0,
      "key": "g",
      "key_class": 19,
      "numeral": "V6/iv"
    },
    {
      "measure": 9,
      "beat": 3.0,
      "key": "g",
      "key_class": 19,
      "numeral": "i/iv"
    },
    {
      "measure": 9,
      "beat": 4.0,
      "key": "g",
      "key_class": 19,
      "numeral": "V6/iv"
    },
    {
      "measure": 10,
      "beat": 1.0,
      "key": "g",
      "key_class": 19,
      "numeral": "i/iv"
    },
    {
      "measure": 10,
      "beat": 2.0,
      "key": "g",
      "key_class": 19,
      "numeral": "V"
    },
    {
      "measure": 10,
      "beat": 3.0,
      "key": "g",
      "key_class": 19,
      "numeral": "iv6[no1][add2]"
    },
    {
      "measure": 10,
      "beat": 4.0,
      "key": "g",
      "key_class": 19,
      "numeral": "iv6"
    },
    {
      "measure": 11,
      "beat": 1.0,
      "key": "g",
      "key_class": 19,
      "numeral": "V"
    },
    {
      "measure": 11,
      "beat": 2.5,
      "key": "g",
      "key_class": 19,
      "numeral": "V2"
    },
    {
      "measure": 11,
      "beat": 3.0,
      "key": "g",
      "key_class": 19,
      "numeral": "i6"
    },
    {
      "measure": 11,
      "beat": 4.0,
      "key": "Bb",
      "key_class": 10,
      "numeral": "vi7"
    },
    {
      "measure": 12,
      "beat": 1.0,
      "key": "Bb",
      "key_class": 10,
      "numeral": "ii"
    },
    {
      "measure": 12,
      "beat": 2.5,
      "key": "Bb",
      "key_class": 10,
      "numeral": "ii2"
    },
    {
      "measure": 12,
      "beat": 3.0,
      "key": "Bb",
      "key_class": 10,
      "numeral": "V6"
    },
    {
      "measure": 12,
      "beat": 4.0,
      "key": "Bb",
      "key_class": 10,
      "numeral": "V7"
    },
    {
      "measure": 13,
      "beat": 1.0,
      "key": "Bb",
      "key_class": 10,
      "numeral": "I"
    },
    {
      "measure": 13,
      "beat": 2.5,
      "key": "Bb",
      "key_class": 10,
      "numeral": "I6"
    },
    {
      "measure": 13,
      "beat": 3.0,
      "key": "Bb",
      "key_class": 10,
      "numeral": "ii7"
    },
    {
      "measure": 13,
      "beat": 4.0,
      "key": "Bb",
      "key_class": 10,
      "numeral": "V7"
    },
    {
      "measure": 14,
      "beat": 1.0,
      "key": "Bb",
      "key_class": 10,
      "numeral": "Id7"
    },
    {
      "measure": 14,
      "beat": 2.0,
      "key": "Bb",
      "key_class": 10,
      "numeral": "vi6"
    },
    {
      "measure": 14,
      "beat": 2.5,
      "key": "Bb",
      "key_class": 10,
      "numeral": "IV"
    },
    {
      "measure": 14,
      "beat": 3.0,
      "key": "Bb",
      "key_class": 10,
      "numeral": "viiø7"
    },
    {
      "measure": 14,
      "beat": 4.0,
      "key": "Bb",
      "key_class": 10,
      "numeral": "iii7"
    },
    {
      "measure": 15,
      "beat": 1.0,
      "key": "Bb",
      "key_class": 10,
      "numeral": "vi7"
    },
    {
      "measure": 15,
      "beat": 2.0,
      "key": "Bb",
      "key_class": 10,
      "numeral": "ii7"
    },
    {
      "measure": 15,
      "beat": 3.0,
      "key": "Bb",
      "key_class": 10,
      "numeral": "V7"
    },
    {
      "measure": 15,
      "beat": 4.0,
      "key": "Bb",
      "key_class": 10,
      "numeral": "I"
    },
    {
      "measure": 15,
      "beat": 4.5,
      "key": "Bb",
      "key_class": 10,
      "numeral": "I6"
    },
    {
      "measure": 16,
      "beat": 1.0,
      "key": "Bb",
      "key_class": 10,
      "numeral": "IV"
    },
    {
      "measure": 16,
      "beat": 1.5,
      "key": "Bb",
      "key_class": 10,
      "numeral": "V7"
    },
    {
      "measure": 16,
      "beat": 2.0,
      "key": "Bb",
      "key_class": 10,
      "numeral": "vi"
    },
    {
      "measure": 16,
      "beat": 2.5,
      "key": "Bb",
      "key_class": 10,
      "numeral": "I6"
    },
    {
      "measure": 16,
      "beat": 3.0,
      "key": "Bb",
      "key_class": 10,
      "numeral": "ii65"
    },
    {
      "measure": 16,
      "beat": 4.0,
      "key": "Bb",
      "key_class": 10,
      "numeral": "V"
    },
    {
      "measure": 17,
      "beat": 1.0,
      "key": "Bb",
      "key_class": 10,
      "numeral": "I"
    },
    {
      "measure": 17,
      "beat": 2.0,
      "key": "g",
      "key_class": 19,
      "numeral": "i6"
    },
    {
      "measure": 17,
      "beat": 3.0,
      "key": "g",
      "key_class": 19,
      "numeral": "iiø65"
    },
    {
      "measure": 17,
      "beat": 4.0,
      "key": "g",
      "key_class": 19,
      "numeral": "V"
    },
    {
      "measure": 18,
      "beat": 1.0,
      "key": "g",
      "key_class": 19,
      "numeral": "i[add9]"
    },
    {
      "measure": 18,
      "beat": 2.0,
      "key": "g",
      "key_class": 19,
      "numeral": "i"
    },
    {
      "measure": 18,
      "beat": 3.0,
      "key": "d",
      "key_class": 14,
      "numeral": "i[no3][add4]"
    },
    {
      "measure": 18,
      "beat": 4.0,
      "key": "d",
      "key_class": 14,
      "numeral": "i"
    },
    {
      "measure": 18,
      "beat": 4.5,
      "key": "d",
      "key_class": 14,
      "numeral": "i6"
    },
    {
      "measure": 19,
      "beat": 1.0,
      "key": "d",
      "key_class": 14,
      "numeral": "ii6[no1][add2]"
    },
    {
      "measure": 19,
      "beat": 2.0,
      "key": "d",
      "key_class": 14,
      "numeral": "ii6"
    },
    {
      "measure": 19,
      "beat": 3.0,
      "key": "d",
      "key_class": 14,
      "numeral": "V7"
    },
    {
      "measure": 19,
      "beat": 4.0,
      "key": "d",
      "key_class": 14,
      "numeral": "i6"
    },
    {
      "measure": 20,
      "beat": 1.0,
      "key": "d",
      "key_class": 14,
      "numeral": "bII6"
    },
    {
      "measure": 20,
      "beat": 1.5,
      "key": "d",
      "key_class": 14,
      "numeral": "V"
    },
    {
      "measure": 20,
      "beat": 2.0,
      "key": "d",
      "key_class": 14,
      "numeral": "iv6"
    },
    {
      "measure": 20,
      "beat": 2.5,
      "key": "d",
      "key_class": 14,
      "numeral": "i6"
    },
    {
      "measure": 20,
      "beat": 3.0,
      "key": "d",
      "key_class": 14,
      "numeral": "iiø65"
    },
    {
      "measure": 20,
      "beat": 4.0,
      "key": "d",
      "key_class": 14,
      "numeral": "V"
    },
    {
      "measure": 21,
      "beat": 1.0,
      "key": "d",
      "key_class": 14,
      "numeral": "i"
    },
    {
      "measure": 21,
      "beat": 3.0,
      "key": "d",
      "key_class": 14,
      "numeral": "V"
    },
    {
      "measure": 22,
      "beat": 1.0,
      "key": "d",
      "key_class": 14,
      "numeral": "i"
    },
    {
      "measure": 22,
      "beat": 3.0,
      "key": "g",
      "key_class": 19,
      "numeral": "V/iv"
    },
    {
      "measure": 23,
      "beat": 1.0,
      "key": "g",
      "key_class": 19,
      "numeral": "iv"
    },
    {
      "measure": 23,
      "beat": 3.0,
      "key": "g",
      "key_class": 19,
      "numeral": "V/III"
    },
    {
      "measure": 24,
      "beat": 1.0,
      "key": "g",
      "key_class": 19,
      "numeral": "III"
    },
    {
      "measure": 24,
      "beat": 3.0,
      "key": "g",
      "key_class": 19,
      "numeral": "V[no3][add4]/III"
    },
    {
      "measure": 24,
      "beat": 4.0,
      "key": "g",
      "key_class": 19,
      "numeral": "V6/III"
    },
    {
      "measure": 24,
      "beat": 4.5,
      "key": "g",
      "key_class": 19,
      "numeral": "V65"
    },
    {
      "measure": 25,
      "beat": 1.0,
      "key": "g",
      "key_class": 19,
      "numeral": "i[add9]"
    },
    {
      "measure": 25,
      "beat": 2.0,
      "key": "g",
      "key_class": 19,
      "numeral": "i6"
    },
    {
      "measure": 25,
      "beat": 3.0,
      "key": "g",
      "key_class": 19,
      "numeral": "V[no3][add4]"
    },
    {
      "measure": 25,
      "beat": 4.0,
      "key": "g",
      "key_class": 19,
      "numeral": "V"
    },
    {
      "measure": 26,
      "beat": 1.0,
      "key": "g",
      "key_class": 19,
      "numeral": "iv6[no1][add2]"
    },
    {
      "measure": 26,
      "beat": 2.0,
      "key": "g",
      "key_class": 19,
      "numeral": "iv6"
    },
    {
      "measure": 26,
      "beat": 3.0,
      "key": "g",
      "key_class": 19,
      "numeral": "V"
    },
    {
      "measure": 26,
      "beat": 4.0,
      "key": "g",
      "key_class": 19,
      "numeral": "Cad64"
    },
    {
      "measure": 27,
      "beat": 1.0,
      "key": "g",
      "key_class": 19,
      "numeral": "V"
    },
    {
      "measure": 27,
      "beat": 2.0,
      "key": "g",
      "key_class": 19,
      "numeral": "Cad64"
    },
    {
      "measure": 27,
      "beat": 3.0,
      "key": "g",
      "key_class": 19,
      "numeral": "V"
    },
    {
      "measure": 27,
      "beat": 4.0,
      "key": "g",
      "key_class": 19,
      "numeral": "Cad64"
    },
    {
      "measure": 28,
      "beat": 1.0,
      "key": "g",
      "key_class": 19,
      "numeral": "V"
    },
    {
      "measure": 28,
      "beat": 2.0,
      "key": "g",
      "key_class": 19,
      "numeral": "Cad64"
    },
    {
      "measure": 28,
      "beat": 3.0,
      "key": "g",
      "key_class": 19,
      "numeral": "V"
    },
    {
      "measure": 28,
      "beat": 4.0,
      "key": "g",
      "key_class": 19,
      "numeral": "V[no5][add6]"
    },
    {
      "measure": 29,
      "beat": 1.0,
      "key": "g",
      "key_class": 19,
      "numeral": "VI"
    },
    {
      "measure": 29,
      "beat": 2.0,
      "key": "g",
      "key_class": 19,
      "numeral": "VI[no5][add6]"
    },
    {
      "measure": 29,
      "beat": 3.0,
      "key": "Bb",
      "key_class": 10,
      "numeral": "V"
    },
    {
      "measure": 29,
      "beat": 4.0,
      "key": "Bb",
      "key_class": 10,
      "numeral": "V[no5][add6]"
    },
    {
      "measure": 30,
      "beat": 1.0,
      "key": "Bb",
      "key_class": 10,
      "numeral": "vi"
    },
    {
      "measure": 30,
      "beat": 2.5,
      "key": "Bb",
      "key_class": 10,
      "numeral": "vi[no5][add6]"
    },
    {
      "measure": 30,
      "beat": 3.0,
      "key": "Bb",
      "key_class": 10,
      "numeral": "V65"
    },
    {
      "measure": 30,
      "beat": 4.0,
      "key": "Bb",
      "key_class": 10,
      "numeral": "I"
    },
    {
      "measure": 30,
      "beat": 4.5,
      "key": "Bb",
      "key_class": 10,
      "numeral": "I6"
    },
    {
      "measure": 31,
      "beat": 1.0,
      "key": "Bb",
      "key_class": 10,
      "numeral": "IV"
    },
    {
      "measure": 31,
      "beat": 1.5,
      "key": "Bb",
      "key_class": 10,
      "numeral": "V7"
    },
    {
      "measure": 31,
      "beat": 2.0,
      "key": "Bb",
      "key_class": 10,
      "numeral": "vi"
    },
    {
      "measure": 31,
      "beat": 2.5,
      "key": "Bb",
      "key_class": 10,
      "numeral": "I6"
    },
    {
      "measure": 31,
      "beat": 3.0,
      "key": "Bb",
      "key_class": 10,
      "numeral": "ii65"
    },
    {
      "measure": 31,
      "beat": 4.0,
      "key": "Bb",
      "key_class": 10,
      "numeral": "V"
    },
    {
      "measure": 32,
      "beat": 1.0,
      "key": "Bb",
      "key_class": 10,
      "numeral": "I"
    },
    {
      "measure": 32,
      "beat": 2.0,
      "key": "g",
      "key_class": 19,
      "numeral": "i6"
    },
    {
      "measure": 32,
      "beat": 3.0,
      "key": "g",
      "key_class": 19,
      "numeral": "IV"
    },
    {
      "measure": 32,
      "beat": 4.0,
      "key": "g",
      "key_class": 19,
      "numeral": "IV[no5][add6]"
    },
    {
      "measure": 33,
      "beat": 1.0,
      "key": "g",
      "key_class": 19,
      "numeral": "V"
    },
    {
      "measure": 33,
      "beat": 2.0,
      "key": "g",
      "key_class": 19,
      "numeral": "V[no5][add6]"
    },
    {
      "measure": 33,
      "beat": 3.0,
      "key": "g",
      "key_class": 19,
      "numeral": "VI"
    },
    {
      "measure": 33,
      "beat": 4.0,
      "key": "g",
      "key_class": 19,
      "numeral": "VI[no5][add6]"
    },
    {
      "measure": 33,
      "beat": 4.5,
      "key": "g",
      "key_class": 19,
      "numeral": "iio6"
    },
    {
      "measure": 34,
      "beat": 1.0,
      "key": "g",
      "key_class": 19,
      "numeral": "V7"
    },
    {
      "measure": 34,
      "beat": 2.0,
      "key": "g",
      "key_class": 19,
      "numeral": "i"
    },
    {
      "measure": 34,
      "beat": 2.5,
      "key": "g",
      "key_class": 19,
      "numeral": "i6"
    },
    {
      "measure": 34,
      "beat": 3.0,
      "key": "g",
      "key_class": 19,
      "numeral": "IV"
    },
    {
      "measure": 34,
      "beat": 3.5,
      "key": "g",
      "key_class": 19,
      "numeral": "V"
    },
    {
      "measure": 34,
      "beat": 4.0,
      "key": "g",
      "key_class": 19,
      "numeral": "VI"
    },
    {
      "measure": 34,
      "beat": 4.5,
      "key": "g",
      "key_class": 19,
      "numeral": "i6"
    },
    {
      "measure": 35,
      "beat": 1.0,
      "key": "g",
      "key_class": 19,
      "numeral": "iiø65"
    },
    {
      "measure": 35,
      "beat": 2.0,
      "key": "Bb",
      "key_class": 10,
      "numeral": "iii"
    },
    {
      "measure": 35,
      "beat": 3.0,
      "key": "Bb",
      "key_class": 10,
      "numeral": "vi65"
    },
    {
      "measure": 35,
      "beat": 4.0,
      "key": "Bb",
      "key_class": 10,
      "numeral": "ii"
    },
    {
      "measure": 36,
      "beat": 1.0,
      "key": "Bb",
      "key_class": 10,
      "numeral": "V65"
    },
    {
      "measure": 36,
      "beat": 2.0,
      "key": "Bb",
      "key_class": 10,
      "numeral": "I"
    },
    {
      "measure": 36,
      "beat": 3.0,
      "key": "Bb",
      "key_class": 10,
      "numeral": "IVd65"
    },
    {
      "measure": 36,
      "beat": 4.0,
      "key": "Bb",
      "key_class": 10,
      "numeral": "viio"
    },
    {
      "measure": 37,
      "beat": 1.0,
      "key": "g",
      "key_class": 19,
      "numeral": "V65"
    },
    {
      "measure": 37,
      "beat": 2.0,
      "key": "g",
      "key_class": 19,
      "numeral": "i"
    },
    {
      "measure": 37,
      "beat": 2.5,
      "key": "g",
      "key_class": 19,
      "numeral": "i6"
    },
    {
      "measure": 37,
      "beat": 3.0,
      "key": "g",
      "key_class": 19,
      "numeral": "iio6[no1][add2]"
    },
    {
      "measure": 37,
      "beat": 4.0,
      "key": "g",
      "key_class": 19,
      "numeral": "iio6"
    },
    {
      "measure": 38,
      "beat": 1.0,
      "key": "g",
      "key_class": 19,
      "numeral": "V7"
    },
    {
      "measure": 38,
      "beat": 2.0,
      "key": "g",
      "key_class": 19,
      "numeral": "Cad64"
    },
    {
      "measure": 38,
      "beat": 3.0,
      "key": "g",
      "key_class": 19,
      "numeral": "V[no3][add4]"
    },
    {
      "measure": 38,
      "beat": 4.0,
      "key": "g",
      "key_class": 19,
      "numeral": "V"
    },
    {
      "measure": 39,
      "beat": 1.0,
      "key": "g",
      "key_class": 19,
      "numeral": "i"
    }
  ],
  "key_regions": [
    {
      "start_measure": 1,
      "end_measure": 10,
      "key": "g",
      "key_class": 19
    },
    {
      "start_measure": 11,
      "end_measure": 16,
      "key": "Bb",
      "key_class": 10
    },
    {
      "start_measure": 17,
      "end_measure": 17,
      "key": "g",
      "key_class": 19
    },
    {
      "start_measure": 18,
      "end_measure": 21,
      "key": "d",
      "key_class": 14
    },
    {
      "start_measure": 22,
      "end_measure": 28,
      "key": "g",
      "key_class": 19
    },
    {
      "start_measure": 29,
      "end_measure": 31,
      "key": "Bb",
      "key_class": 10
    },
    {
      "start_measure": 32,
      "end_measure": 34,
      "key": "g",
      "key_class": 19
    },
    {
      "start_measure": 35,
      "end_measure": 36,
      "key": "Bb",
      "key_class": 10
    },
    {
      "start_measure": 37,
      "end_measure": 39,
      "key": "g",
      "key_class": 19
    }
  ],
  "statistics": {
    "total_annotations": 160,
    "unique_keys": 3,
    "major_annotations": 47,
    "minor_annotations": 113
  }
}