{
  "source": "when_in_rome",
  "file_path": "Corpus/Variations_and_Grounds/Purcell,_Henry/_/Chacony_Z730/analysis.txt",
  "piece_id": "purcell_chacony_z730",
  "global_key": "g",
  "global_key_class": 19,
  "annotations": [
    {
      "measure": 1,
      "beat": 1.0,
      "key": "g",
      "key_class": 19,
      "numeral": "i"
    },
    {
      "measure": 2,
      "beat": 1.0,
      "key": "g",
      "key_class": 19,
      "numeral": "V6"
    },
    {
      "measure": 3,
      "beat": 1.0,
      "key": "g",
      "key_class": 19,
      "numeral": "i"
    },
    {
      "measure": 3,
      "beat": 2.0,
      "key": "g",
      "key_class": 19,
      "numeral": "iv6"
    },
    {
      "measure": 4,
      "beat": 1.0,
      "key": "g",
      "key_class": 19,
      "numeral": "V"
    },
    {
      "measure": 5,
      "beat": 1.0,
      "key": "g",
      "key_class": 19,
      "numeral": "V6/iv"
    },
    {
      "measure": 6,
      "beat": 1.0,
      "key": "g",
      "key_class": 19,
      "numeral": "iv"
    },
    {
      "measure": 7,
      "beat": 1.0,
      "key": "g",
      "key_class": 19,
      "numeral": "i64"
    },
    {
      "measure": 7,
      "beat": 3.0,
      "key": "g",
      "key_class": 19,
      "numeral": "V7"
    },
    {
      "measure": 8,
      "beat": 1.0,
      "key": "g",
      "key_class": 19,
      "numeral": "i"
    },
    {
      "measure": 9,
      "beat": 1.0,
      "key": "g",
      "key_class": 19,
      "numeral": "i"
    },
    {
      "measure": 9,
      "beat": 2.0,
      "key": "g",
      "key_class": 19,
      "numeral": "VI6"
    },
    {
      "measure": 10,
      "beat": 1.0,
      "key": "g",
      "key_class": 19,
      "numeral": "viio7"
    },
    {
      "measure": 10,
      "beat": 2.0,
      "key": "g",
      "key_class": 19,
      "numeral": "V65"
    },
    {
      "measure": 11,
      "beat": 1.0,
      "key": "g",
      "key_class": 19,
      "numeral": "i"
    },
    {
      "measure": 11,
      "beat": 2.0,
      "key": "g",
      "key_class": 19,
      "numeral": "iv6"
    },
    {
      "measure": 11,
      "beat": 3.5,
      "key": "g",
      "key_class": 19,
      "numeral": "iiø64"
    },
    {
      "measure": 12,
      "beat": 1.0,
      "key": "g",
      "key_class": 19,
      "numeral": "V"
    },
    {
      "measure": 13,
      "beat": 1.0,
      "key": "g",
      "key_class": 19,
      "numeral": "V65/iv"
    },
    {
      "measure": 14,
      "beat": 1.0,
      "key": "g",
      "key_class": 19,
      "numeral": "IV"
    },
    {
      "measure": 14,
      "beat": 2.0,
      "key": "g",
      "key_class": 19,
      "numeral": "viio43"
    },
    {
      "measure": 15,
      "beat": 1.0,
      "key": "g",
      "key_class": 19,
      "numeral": "V"
    },
    {
      "measure": 16,
      "beat": 1.0,
      "key": "g",
      "key_class": 19,
      "numeral": "i"
    },
    {
      "measure": 17,
      "beat": 1.0,
      "key": "g",
      "key_class": 19,
      "numeral": "i"
    },
    {
      "measure": 18,
      "beat": 1.0,
      "key": "g",
      "key_class": 19,
      "numeral": "V6"
    },
    {
      "measure": 19,
      "beat": 1.0,
      "key": "g",
      "key_class": 19,
      "numeral": "i"
    },
    {
      "measure": 19,
      "beat": 2.0,
      "key": "g",
      "key_class": 19,
      "numeral": "iv6"
    },
    {
      "measure": 20,
      "beat": 1.0,
      "key": "g",
      "key_class": 19,
      "numeral": "V"
    },
    {
      "measure": 21,
      "beat": 1.0,
      "key": "g",
      "key_class": 19,
      "numeral": "V6/iv"
    },
    {
      "measure": 22,
      "beat": 1.0,
      "key": "g",
      "key_class": 19,
      "numeral": "iv"
    },
    {
      "measure": 23,
      "beat": 1.0,
      "key": "g",
      "key_class": 19,
      "numeral": "i64"
    },
    {
      "measure": 23,
      "beat": 3.0,
      "key": "g",
      "key_class": 19,
      "numeral": "V7"
    },
    {
      "measure": 24,
      "beat": 1.0,
      "key": "g",
      "key_class": 19,
      "numeral": "i"
    },
    {
      "measure": 25,
      "beat": 1.0,
      "key": "g",
      "key_class": 19,
      "numeral": "i"
    },
    {
      "measure": 26,
      "beat": 1.0,
      "key": "g",
      "key_class": 19,
      "numeral": "V6"
    },
    {
      "measure": 27,
      "beat": 1.0,
      "key": "g",
      "key_class": 19,
      "numeral": "i"
    },
    {
      "measure": 27,
      "beat": 2.0,
      "key": "g",
      "key_class": 19,
      "numeral": "iv6"
    },
    {
      "measure": 28,
      "beat": 1.0,
      "key": "g",
      "key_class": 19,
      "numeral": "V"
    },
    {
      "measure": 29,
      "beat": 1.0,
      "key": "g",
      "key_class": 19,
      "numeral": "V6/iv"
    },
    {
      "measure": 30,
      "beat": 1.0,
      "key": "g",
      "key_class": 19,
      "numeral": "iv"
    },
    {
      "measure": 31,
      "beat": 1.0,
      "key": "g",
      "key_class": 19,
      "numeral": "V7"
    },
    {
      "measure": 32,
      "beat": 1.0,
      "key": "g",
      "key_class": 19,
      "numeral": "I"
    },
    {
      "measure": 33,
      "beat": 1.0,
      "key": "g",
      "key_class": 19,
      "numeral": "V42/V"
    },
    {
      "measure": 34,
      "beat": 1.0,
      "key": "g",
      "key_class": 19,
      "numeral": "V6"
    },
    {
      "measure": 35,
      "beat": 1.0,
      "key": "g",
      "key_class": 19,
      "numeral": "i"
    },
    {
      "measure": 35,
      "beat": 2.0,
      "key": "g",
      "key_class": 19,
      "numeral": "iv6"
    },
    {
      "measure": 36,
      "beat": 1.0,
      "key": "g",
      "key_class": 19,
      "numeral": "ii7/iv"
    },
    {
      "measure": 37,
      "beat": 1.0,
      "key": "g",
      "key_class": 19,
      "numeral": "V6/iv"
    },
    {
      "measure": 38,
      "beat": 1.0,
      "key": "g",
      "key_class": 19,
      "numeral": "ii65"
    },
    {
      "measure": 39,
      "beat": 1.0,
      "key": "g",
      "key_class": 19,
      "numeral": "i64"
    },
    {
      "measure": 39,
      "beat": 3.5,
      "key": "g",
      "key_class": 19,
      "numeral": "V"
    },
    {
      "measure": 40,
      "beat": 1.0,
      "key": "g",
      "key_class": 19,
      "numeral": "i"
    },
    {
      "measure": 41,
      "beat": 1.0,
      "key": "g",
      "key_class": 19,
      "numeral": "i"
    },
    {
      "measure": 41,
      "beat": 2.0,
      "key": "g",
      "key_class": 19,
      "numeral": "VII"
    },
    {
      "measure": 41,
      "beat": 3.0,
      "key": "g",
      "key_class": 19,
      "numeral": "VI"
    },
    {
      "measure": 42,
      "beat": 1.0,
      "key": "g",
      "key_class": 19,
      "numeral": "V"
    },
    {
      "measure": 43,
      "beat": 1.0,
      "key": "g",
      "key_class": 19,
      "numeral": "VI"
    },
    {
      "measure": 43,
      "beat": 2.0,
      "key": "g",
      "key_class": 19,
      "numeral": "V/III"
    },
    {
      "measure": 44,
      "beat": 1.0,
      "key": "g",
      "key_class": 19,
      "numeral": "III"
    },
    {
      "measure": 45,
      "beat": 1.0,
      "key": "g",
      "key_class": 19,
      "numeral": "V7/iv"
    },
    {
      "measure": 46,
      "beat": 1.0,
      "key": "g",
      "key_class": 19,
      "numeral": "iv"
    },
    {
      "measure": 46,
      "beat": 2.0,
      "key": "g",
      "key_class": 19,
      "numeral": "iio6"
    },
    {
      "measure": 47,
      "beat": 1.0,
      "key": "g",
      "key_class": 19,
      "numeral": "III+7"
    },
    {
      "measure": 47,
      "beat": 3.0,
      "key": "g",
      "key_class": 19,
      "numeral": "V42"
    },
    {
      "measure": 48,
      "beat": 1.0,
      "key": "g",
      "key_class": 19,
      "numeral": "I6"
    },
    {
      "measure": 49,
      "beat": 1.0,
      "key": "d",
      "key_class": 14,
      "numeral": "VI7"
    },
    {
      "measure": 50,
      "beat": 1.0,
      "key": "d",
      "key_class": 14,
      "numeral": "V"
    },
    {
      "measure": 50,
      "beat": 3.0,
      "key": "d",
      "key_class": 14,
      "numeral": "i64"
    },
    {
      "measure": 51,
      "beat": 1.0,
      "key": "d",
      "key_class": 14,
      "numeral": "iv7"
    },
    {
      "measure": 52,
      "beat": 1.0,
      "key": "d",
      "key_class": 14,
      "numeral": "V"
    },
    {
      "measure": 53,
      "beat": 1.0,
      "key": "d",
      "key_class": 14,
      "numeral": "I"
    },
    {
      "measure": 54,
      "beat": 1.0,
      "key": "g",
      "key_class": 19,
      "numeral": "i"
    },
    {
      "measure": 55,
      "beat": 1.0,
      "key": "g",
      "key_class": 19,
      "numeral": "V6"
    },
    {
      "measure": 56,
      "beat": 1.0,
      "key": "g",
      "key_class": 19,
      "numeral": "i"
    },
    {
      "measure": 56,
      "beat": 2.0,
      "key": "g",
      "key_class": 19,
      "numeral": "VI7"
    },
    {
      "measure": 57,
      "beat": 1.0,
      "key": "g",
      "key_class": 19,
      "numeral": "V"
    },
    {
      "measure": 58,
      "beat": 1.0,
      "key": "g",
      "key_class": 19,
      "numeral": "V6/iv"
    },
    {
      "measure": 59,
      "beat": 1.0,
      "key": "g",
      "key_class": 19,
      "numeral": "iv"
    },
    {
      "measure": 60,
      "beat": 1.0,
      "key": "g",
      "key_class": 19,
      "numeral": "i64"
    },
    {
      "measure": 60,
      "beat": 3.5,
      "key": "g",
      "key_class": 19,
      "numeral": "V7"
    },
    {
      "measure": 61,
      "beat": 1.0,
      "key": "g",
      "key_class": 19,
      "numeral": "i"
    },
    {
      "measure": 62,
      "beat": 1.0,
      "key": "g",
      "key_class": 19,
      "numeral": "i"
    },
    {
      "measure": 63,
      "beat": 1.0,
      "key": "g",
      "key_class": 19,
      "numeral": "viio6"
    },
    {
      "measure": 64,
      "beat": 1.0,
      "key": "g",
      "key_class": 19,
      "numeral": "i"
    },
    {
      "measure": 64,
      "beat": 2.0,
      "key": "g",
      "key_class": 19,
      "numeral": "VI6"
    },
    {
      "measure": 65,
      "beat": 1.0,
      "key": "g",
      "key_class": 19,
      "numeral": "V"
    },
    {
      "measure": 66,
      "beat": 1.0,
      "key": "g",
      "key_class": 19,
      "numeral": "V6/iv"
    },
    {
      "measure": 67,
      "beat": 1.0,
      "key": "g",
      "key_class": 19,
      "numeral": "iv"
    },
    {
      "measure": 68,
      "beat": 1.0,
      "key": "g",
      "key_class": 19,
      "numeral": "i64"
    },
    {
      "measure": 68,
      "beat": 3.0,
      "key": "g",
      "key_class": 19,
      "numeral": "V7"
    },
    {
      "measure": 69,
      "beat": 1.0,
      "key": "g",
      "key_class": 19,
      "numeral": "i"
    },
    {
      "measure": 70,
      "beat": 1.0,
      "key": "g",
      "key_class": 19,
      "numeral": "i"
    },
    {
      "measure": 71,
      "beat": 1.0,
      "key": "g",
      "key_class": 19,
      "numeral": "V6"
    },
    {
      "measure": 72,
      "beat": 1.0,
      "key": "g",
      "key_class": 19,
      "numeral": "i"
    },
    {
      "measure": 72,
      "beat": 2.0,
      "key": "g",
      "key_class": 19,
      "numeral": "VI"
    },
    {
      "measure": 72,
      "beat": 3.5,
      "key": "g",
      "key_class": 19,
      "numeral": "iiø64"
    },
    {
      "measure": 73,
      "beat": 1.0,
      "key": "g",
      "key_class": 19,
      "numeral": "V"
    },
    {
      "measure": 74,
      "beat": 1.0,
      "key": "g",
      "key_class": 19,
      "numeral": "V6/iv"
    },
    {
      "measure": 75,
      "beat": 1.0,
      "key": "g",
      "key_class": 19,
      "numeral": "iv"
    },
    {
      "measure": 76,
      "beat": 1.0,
      "key": "g",
      "key_class": 19,
      "numeral": "V7"
    },
    {
      "measure": 77,
      "beat": 1.0,
      "key": "g",
      "key_class": 19,
      "numeral": "i"
    },
    {
      "measure": 77,
      "beat": 3.0,
      "key": "g",
      "key_class": 19,
      "numeral": "viio6"
    },
    {
      "measure": 78,
      "beat": 1.0,
      "key": "g",
      "key_class": 19,
      "numeral": "i"
    },
    {
      "measure": 79,
      "beat": 1.0,
      "key": "g",
      "key_class": 19,
      "numeral": "V6"
    },
    {
      "measure": 80,
      "beat": 1.0,
      "key": "g",
      "key_class": 19,
      "numeral": "i"
    },
    {
      "measure": 80,
      "beat": 2.0,
      "key": "g",
      "key_class": 19,
      "numeral": "iv6"
    },
    {
      "measure": 81,
      "beat": 1.0,
      "key": "g",
      "key_class": 19,
      "numeral": "V"
    },
    {
      "measure": 82,
      "beat": 1.0,
      "key": "g",
      "key_class": 19,
      "numeral": "V6/iv"
    },
    {
      "measure": 83,
      "beat": 1.0,
      "key": "g",
      "key_class": 19,
      "numeral": "iv"
    },
    {
      "measure": 84,
      "beat": 1.0,
      "key": "g",
      "key_class": 19,
      "numeral": "V7"
    },
    {
      "measure": 85,
      "beat": 1.0,
      "key": "g",
      "key_class": 19,
      "numeral": "i"
    },
    {
      "measure": 86,
      "beat": 1.0,
      "key": "g",
      "key_class": 19,
      "numeral": "i"
    },
    {
      "measure": 86,
      "beat": 2.0,
      "key": "g",
      "key_class": 19,
      "numeral": "V42/V"
    },
    {
      "measure": 87,
      "beat": 1.0,
      "key": "g",
      "key_class": 19,
      "numeral": "V65"
    },
    {
      "measure": 88,
      "beat": 1.0,
      "key": "g",
      "key_class": 19,
      "numeral": "i"
    },
    {
      "measure": 88,
      "beat": 2.0,
      "key": "g",
      "key_class": 19,
      "numeral": "iv6"
    },
    {
      "measure": 89,
      "beat": 1.0,
      "key": "g",
      "key_class": 19,
      "numeral": "i64"
    },
    {
      "measure": 89,
      "beat": 2.0,
      "key": "g",
      "key_class": 19,
      "numeral": "V"
    },
    {
      "measure": 90,
      "beat": 1.0,
      "key": "g",
      "key_class": 19,
      "numeral": "V6/iv"
    },
    {
      "measure": 91,
      "beat": 1.0,
      "key": "g",
      "key_class": 19,
      "numeral": "iv"
    },
    {
      "measure": 92,
      "beat": 1.0,
      "key": "g",
      "key_class": 19,
      "numeral": "i64"
    },
    {
      "measure": 92,
      "beat": 3.0,
      "key": "g",
      "key_class": 19,
      "numeral": "V7"
    },
    {
      "measure": 93,
      "beat": 1.0,
      "key": "g",
      "key_class": 19,
      "numeral": "i"
    },
    {
      "measure": 94,
      "beat": 1.0,
      "key": "g",
      "key_class": 19,
      "numeral": "i"
    },
    {
      "measure": 95,
      "beat": 1.0,
      "key": "g",
      "key_class": 19,
      "numeral": "V6"
    },
    {
      "measure": 96,
      "beat": 1.0,
      "key": "g",
      "key_class": 19,
      "numeral": "i"
    },
    {
      "measure": 96,
      "beat": 2.0,
      "key": "g",
      "key_class": 19,
      "numeral": "VI"
    },
    {
      "measure": 97,
      "beat": 1.0,
      "key": "g",
      "key_class": 19,
      "numeral": "V"
    },
    {
      "measure": 98,
      "beat": 1.0,
      "key": "g",
      "key_class": 19,
      "numeral": "V6/iv"
    },
    {
      "measure": 99,
      "beat": 1.0,
      "key": "g",
      "key_class": 19,
      "numeral": "iv"
    },
    {
      "measure": 100,
      "beat": 1.0,
      "key": "g",
      "key_class": 19,
      "numeral": "V7"
    },
    {
      "measure": 101,
      "beat": 1.0,
      "key": "g",
      "key_class": 19,
      "numeral": "i"
    },
    {
      "measure": 102,
      "beat": 1.0,
      "key": "g",
      "key_class": 19,
      "numeral": "i"
    },
    {
      "measure": 103,
      "beat": 1.0,
      "key": "g",
      "key_class": 19,
      "numeral": "V6"
    },
    {
      "measure": 104,
      "beat": 1.0,
      "key": "g",
      "key_class": 19,
      "numeral": "V/iv"
    },
    {
      "measure": 104,
      "beat": 2.0,
      "key": "g",
      "key_class": 19,
      "numeral": "iv6"
    },
    {
      "measure": 105,
      "beat": 1.0,
      "key": "g",
      "key_class": 19,
      "numeral": "V"
    },
    {
      "measure": 106,
      "beat": 1.0,
      "key": "g",
      "key_class": 19,
      "numeral": "V65/iv"
    },
    {
      "measure": 107,
      "beat": 1.0,
      "key": "g",
      "key_class": 19,
      "numeral": "iv"
    },
    {
      "measure": 108,
      "beat": 1.0,
      "key": "g",
      "key_class": 19,
      "numeral": "V7"
    },
    {
      "measure": 109,
      "beat": 1.0,
      "key": "g",
      "key_class": 19,
      "numeral": "i"
    },
    {
      "measure": 109,
      "beat": 3.0,
      "key": "g",
      "key_class": 19,
      "numeral": "VI6"
    },
    {
      "measure": 110,
      "beat": 1.0,
      "key": "Bb",
      "key_class": 10,
      "numeral": "V65"
    },
    {
      "measure": 111,
      "beat": 1.0,
      "key": "Bb",
      "key_class": 10,
      "numeral": "I"
    },
    {
      "measure": 111,
      "beat": 2.0,
      "key": "Bb",
      "key_class": 10,
      "numeral": "IV"
    },
    {
      "measure": 112,
      "beat": 1.0,
      "key": "c",
      "key_class": 12,
      "numeral": "iio65"
    },
    {
      "measure": 113,
      "beat": 1.0,
      "key": "c",
      "key_class": 12,
      "numeral": "V9"
    },
    {
      "measure": 113,
      "beat": 2.0,
      "key": "c",
      "key_class": 12,
      "numeral": "III+6"
    },
    {
      "measure": 114,
      "beat": 1.0,
      "key": "c",
      "key_class": 12,
      "numeral": "iv6"
    },
    {
      "measure": 115,
      "beat": 1.0,
      "key": "c",
      "key_class": 12,
      "numeral": "V"
    },
    {
      "measure": 116,
      "beat": 1.0,
      "key": "c",
      "key_class": 12,
      "numeral": "iv7"
    },
    {
      "measure": 117,
      "beat": 1.0,
      "key": "c",
      "key_class": 12,
      "numeral": "V"
    },
    {
      "measure": 118,
      "beat": 1.0,
      "key": "Bb",
      "key_class": 10,
      "numeral": "V/V"
    },
    {
      "measure": 118,
      "beat": 3.0,
      "key": "Bb",
      "key_class": 10,
      "numeral": "vii"
    },
    {
      "measure": 119,
      "beat": 1.0,
      "key": "Bb",
      "key_class": 10,
      "numeral": "iii"
    },
    {
      "measure": 119,
      "beat": 3.0,
      "key": "Bb",
      "key_class": 10,
      "numeral": "I"
    },
    {
      "measure": 120,
      "beat": 1.0,
      "key": "Bb",
      "key_class": 10,
      "numeral": "IV"
    },
    {
      "measure": 120,
      "beat": 3.0,
      "key": "Bb",
      "key_class": 10,
      "numeral": "ii"
    },
    {
      "measure": 121,
      "beat": 1.0,
      "key": "Bb",
      "key_class": 10,
      "numeral": "V"
    },
    {
      "measure": 122,
      "beat": 1.0,
      "key": "Bb",
      "key_class": 10,
      "numeral": "I"
    },
    {
      "measure": 123,
      "beat": 1.0,
      "key": "g",
      "key_class": 19,
      "numeral": "i"
    },
    {
      "measure": 124,
      "beat": 1.0,
      "key": "g",
      "key_class": 19,
      "numeral": "V6"
    },
    {
      "measure": 125,
      "beat": 1.0,
      "key": "g",
      "key_class": 19,
      "numeral": "i"
    },
    {
      "measure": 125,
      "beat": 2.0,
      "key": "g",
      "key_class": 19,
      "numeral": "iv6"
    },
    {
      "measure": 126,
      "beat": 1.0,
      "key": "g",
      "key_class": 19,
      "numeral": "V"
    },
    {
      "measure": 127,
      "beat": 1.0,
      "key": "g",
      "key_class": 19,
      "numeral": "V6/iv"
    },
    {
      "measure": 128,
      "beat": 1.0,
      "key": "g",
      "key_class": 19,
      "numeral": "iv"
    },
    {
      "measure": 129,
      "beat": 1.0,
      "key": "g",
      "key_class": 19,
      "numeral": "V7"
    },
    {
      "measure": 130,
      "beat": 1.0,
      "key": "g",
      "key_class": 19,
      "numeral": "i"
    },
    {
      "measure": 131,
      "beat": 1.0,
      "key": "g",
      "key_class": 19,
      "numeral": "i"
    },
    {
      "measure": 132,
      "beat": 1.0,
      "key": "g",
      "key_class": 19,
      "numeral": "V6"
    },
    {
      "measure": 133,
      "beat": 1.0,
      "key": "g",
      "key_class": 19,
      "numeral": "i"
    },
    {
      "measure": 133,
      "beat": 2.0,
      "key": "g",
      "key_class": 19,
      "numeral": "iv6"
    },
    {
      "measure": 134,
      "beat": 1.0,
      "key": "g",
      "key_class": 19,
      "numeral": "V"
    },
    {
      "measure": 135,
      "beat": 1.0,
      "key": "g",
      "key_class": 19,
      "numeral": "V6/iv"
    },
    {
      "measure": 136,
      "beat": 1.0,
      "key": "g",
      "key_class": 19,
      "numeral": "iv"
    },
    {
      "measure": 137,
      "beat": 1.0,
      "key": "g",
      "key_class": 19,
      "numeral": "i64"
    },
    {
      "measure": 137,
      "beat": 3.5,
      "key": "g",
      "key_class": 19,
      "numeral": "V7"
    },
    {
      "measure": 138,
      "beat": 1.0,
      "key": "g",
      "key_class": 19,
      "numeral": "i"
    },
    {
      "measure": 139,
      "beat": 1.0,
      "key": "g",
      "key_class": 19,
      "numeral": "i"
    },
    {
      "measure": 139,
      "beat": 2.0,
      "key": "g",
      "key_class": 19,
      "numeral": "iiø42"
    },
    {
      "measure": 140,
      "beat": 1.0,
      "key": "g",
      "key_class": 19,
      "numeral": "V6"
    },
    {
      "measure": 141,
      "beat": 1.0,
      "key": "g",
      "key_class": 19,
      "numeral": "i"
    },
    {
      "measure": 141,
      "beat": 2.0,
      "key": "g",
      "key_class": 19,
      "numeral": "iiø43"
    },
    {
      "measure": 142,
      "beat": 1.0,
      "key": "g",
      "key_class": 19,
      "numeral": "V"
    },
    {
      "measure": 143,
      "beat": 1.0,
      "key": "g",
      "key_class": 19,
      "numeral": "V6/iv"
    },
    {
      "measure": 144,
      "beat": 1.0,
      "key": "g",
      "key_class": 19,
      "numeral": "iv"
    },
    {
      "measure": 145,
      "beat": 1.0,
      "key": "g",
      "key_class": 19,
      "numeral": "V7"
    },
    {
      "measure": 146,
      "beat": 1.0,
      "key": "g",
      "key_class": 19,
      "numeral": "i"
    },
    {
      "measure": 147,
      "beat": 1.0,
      "key": "g",
      "key_class": 19,
      "numeral": "i"
    },
    {
      "measure": 147,
      "beat": 2.0,
      "key": "g",
      "key_class": 19,
      "numeral": "iiø42"
    },
    {
      "measure": 148,
      "beat": 1.0,
      "key": "g",
      "key_class": 19,
      "numeral": "V6"
    },
    {
      "measure": 149,
      "beat": 1.0,
      "key": "g",
      "key_class": 19,
      "numeral": "i"
    },
    {
      "measure": 149,
      "beat": 2.0,
      "key": "g",
      "key_class": 19,
      "numeral": "iiø43"
    },
    {
      "measure": 150,
      "beat": 1.0,
      "key": "g",
      "key_class": 19,
      "numeral": "V"
    },
    {
      "measure": 151,
      "beat": 1.0,
      "key": "g",
      "key_class": 19,
      "numeral": "V6/iv"
    },
    {
      "measure": 152,
      "beat": 1.0,
      "key": "g",
      "key_class": 19,
      "numeral": "iv"
    },
    {
      "measure": 153,
      "beat": 1.0,
      "key": "g",
      "key_class": 19,
      "numeral": "V7"
    },
    {
      "measure": 154,
      "beat": 1.0,
      "key": "g",
      "key_class": 19,
      "numeral": "i"
    }
  ],
  "key_regions": [
    {
      "start_measure": 1,
      "end_measure": 48,
      "key": "g",
      "key_class": 19
    },
    {
      "start_measure": 49,
      "end_measure": 53,
      "key": "d",
      "key_class": 14
    },
    {
      "start_measure": 54,
      "end_measure": 109,
      "key": "g",
      "key_class": 19
    },
    {
      "start_measure": 110,
      "end_measure": 111,
      "key": "Bb",
      "key_class": 10
    },
    {
      "start_measure": 112,
      "end_measure": 117,
      "key": "c",
      "key_class": 12
    },
    {
      "start_measure": 118,
      "end_measure": 122,
      "key": "Bb",
      "key_class": 10
    },
    {
      "start_measure": 123,
      "end_measure": 154,
      "key": "g",
      "key_class": 19
    }
  ],
  "statistics": {
    "total_annotations": 199,
    "unique_keys": 4,
    "major_annotations": 11,
    "minor_annotations": 188
  }
}